zubr/__init__.py
zubr/zubrbyin.py
zubrby-1.1.13.dist-info/LICENSE
zubrby-1.1.13.dist-info/METADATA
zubrby-1.1.13.dist-info/WHEEL
zubrby-1.1.13.dist-info/top_level.txt
zubrby-1.1.13.dist-info/RECORD
