Metadata-Version: 2.1
Name: zubrby
Version: 1.1.13
Summary: This is the simplest module for quick work with files.
Home-page: https://github.com/stncc-bit
Author: aliaksei_ivanko
Author-email: aleksei.ivanko@gmail.com
Project-URL: GitHub, https://github.com/stncc-bit
Keywords: files zubr
Classifier: Programming Language :: Python :: 3.11
Classifier: License :: OSI Approved :: MIT License
Classifier: Operating System :: OS Independent
Requires-Python: >=3.12
License-File: LICENSE
Requires-Dist: requests >=2.25.1
